common_utils-2.0.1.dev1.dist-info/DESCRIPTION.rst
common_utils-2.0.1.dev1.dist-info/METADATA
common_utils-2.0.1.dev1.dist-info/RECORD
common_utils-2.0.1.dev1.dist-info/WHEEL
common_utils-2.0.1.dev1.dist-info/metadata.json
common_utils-2.0.1.dev1.dist-info/top_level.txt
utils/__init__.py
utils/ascheduler.py
utils/calendar.py
utils/cmd.py
utils/errors.py
utils/rsync.py
