Metadata-Version: 2.0
Name: common-utils
Version: 2.0.1.dev1
Summary: A common utils project
Home-page: https://github.com/calvinjiang/common-utils
Author: Calvin Jiang
Author-email: jianghuachinacom@163.com
License: MIT
Keywords: python common utils
Platform: UNKNOWN
Classifier: Development Status :: 4 - Beta
Classifier: Intended Audience :: Developers
Classifier: Topic :: Software Development :: Build Tools
Classifier: License :: OSI Approved :: MIT License
Classifier: Programming Language :: Python :: 2.6
Classifier: Programming Language :: Python :: 2.7
Classifier: Programming Language :: Python :: 3
Classifier: Programming Language :: Python :: 3.3
Classifier: Programming Language :: Python :: 3.4
Classifier: Programming Language :: Python :: 3.5
